{"name":"生肖传奇之十二生肖闯江湖","id":31316,"url":"http://www.kumi.cn/webapp/player.php?contentid=37852&vod=1","category":9,"brief":"讲述十二生肖与紫魁星大战年魔之前，天庭、人间的传奇","desc":"故事讲述的是在十二生肖与紫魁星大战年魔之前，天庭、人间上演的一段更为玄幻的圣兽选拔传奇。远古时期，天地一片混沌，还没有完全成形，人世间一片混乱、骚动。人间界形成之初，人类还没有计时、计年的观念，人们总是忘记自己出生在哪一年，过了多少岁，完全没有辈分的观念。为了解决人类的困扰，仙界的统治者玉皇大帝想出个好办法，决定用动物名称来代表年份。于是，玉皇大帝派遣信使信天翁广发英雄帖，召集动物界的各路英雄好汉参与遴选，以选出十二只动物担任生肖属相。一部时空流转的上古史诗巨作，一段亦庄亦谐的生肖历险传说。《生肖传奇之十二生肖闯江湖》，与你一起笑傲悠远神奇的远古，亲历精妙绝伦的功夫，领悟中华文化之典故。","mode":1,"ver":"1048576","exinfo":{},"width":"800","height":"600"}